{"chunk_definitions":[{"row":9,"row_count":1,"visible":true,"expansion_state":0,"options":{"engine":"r","label":"setup","include":false},"document_id":"7CAC5BD3","chunk_id":"csetup_chunk","chunk_label":"setup"},{"row":104,"row_count":1,"visible":true,"expansion_state":0,"options":{"engine":"r","label":"load_data","include":false},"document_id":"7CAC5BD3","chunk_id":"cmlz2yv22e4hx","chunk_label":"unnamed-chunk-2"},{"row":201,"row_count":1,"visible":true,"expansion_state":0,"options":{"engine":"r","label":"make_base_figs"},"document_id":"AF069983","chunk_id":"c69fr0p0g4op8","chunk_label":"unnamed-chunk-3"},{"row":245,"row_count":1,"visible":true,"expansion_state":0,"options":{"engine":"r","label":"study_1","fig.width":6,"fig.asp":0.5},"document_id":"AF069983","chunk_id":"crm11zrr6lb3i","chunk_label":"study_1"},{"row":262,"row_count":1,"visible":true,"expansion_state":0,"options":{"engine":"r","include":false,"label":"unnamed-chunk-8"},"document_id":"AF069983","chunk_id":"cykbnojqx7vgc","chunk_label":"unnamed-chunk-4"},{"row":302,"row_count":1,"visible":true,"expansion_state":0,"options":{"engine":"r","label":"study_2","fig.width":6,"fig.asp":0.5},"document_id":"AF069983","chunk_id":"czgct2s66egxg","chunk_label":"study_2"},{"row":342,"row_count":1,"visible":true,"expansion_state":0,"options":{"engine":"r","label":"study_3","fig.width":6,"fig.asp":0.5},"document_id":"AF069983","chunk_id":"cvxo51izxamy8","chunk_label":"study_3"},{"row":388,"row_count":1,"visible":true,"expansion_state":0,"options":{"engine":"r","label":"study_4a","fig.width":6,"fig.asp":0.5},"document_id":"AF069983","chunk_id":"csamy1ixojuii","chunk_label":"study_4a"},{"row":425,"row_count":1,"visible":true,"expansion_state":0,"options":{"engine":"r","label":"study_4b","fig.width":6,"fig.asp":0.5},"document_id":"AF069983","chunk_id":"cd5xx5lzm36nn","chunk_label":"study_4b"},{"row":462,"row_count":1,"visible":true,"expansion_state":0,"options":{"engine":"r","label":"study_4c","fig.width":6,"fig.asp":0.5},"document_id":"AF069983","chunk_id":"chy4s3rdeqlgt","chunk_label":"study_4c"},{"row":500,"row_count":1,"visible":true,"expansion_state":0,"options":{"engine":"r","label":"study_4d","fig.width":6,"fig.asp":0.5},"document_id":"AF069983","chunk_id":"cczcgpnorzhz0","chunk_label":"study_4d"},{"row":521,"row_count":1,"visible":true,"expansion_state":0,"options":{"engine":"r","label":"unnamed-chunk-7"},"document_id":"AF069983","chunk_id":"cjnb2k3si2min","chunk_label":"unnamed-chunk-6"},{"row":570,"row_count":1,"visible":true,"expansion_state":0,"options":{"engine":"r","echo":false,"label":"unnamed-chunk-30"},"document_id":"AF069983","chunk_id":"cvpaepiw9vn3g","chunk_label":"unnamed-chunk-7"},{"row":588,"row_count":1,"visible":true,"expansion_state":0,"options":{"engine":"r","fig.asp":0.8,"fig.width":3,"label":"unnamed-chunk-261"},"document_id":"AF069983","chunk_id":"cf07ux3m2apzw","chunk_label":"unnamed-chunk-8"},{"row":604,"row_count":1,"visible":true,"expansion_state":0,"options":{"engine":"r","echo":true,"label":"unnamed-chunk-275"},"document_id":"AF069983","chunk_id":"ca60xeepr0rtg","chunk_label":"unnamed-chunk-9"},{"row":675,"row_count":1,"visible":true,"expansion_state":0,"options":{"engine":"r","fig.asp":0.8,"fig.width":3,"echo":false,"label":"unnamed-chunk-285"},"document_id":"AF069983","chunk_id":"cmqnzmf7gqm3u","chunk_label":"unnamed-chunk-12"}],"doc_write_time":1631222246,"working_dir":null,"default_chunk_options":{"error":false,"echo":false,"warning":false,"message":false},"chunk_rendered_width":488}